newscleaner/__init__.py
newscleaner/cleaner.py
newscleaner/setup.py
newscleaner/strip_clean.py
newscleaner-0.2.0.dist-info/LICENCE.txt
newscleaner-0.2.0.dist-info/METADATA
newscleaner-0.2.0.dist-info/PKG-INFO.txt
newscleaner-0.2.0.dist-info/WHEEL
newscleaner-0.2.0.dist-info/top_level.txt
newscleaner-0.2.0.dist-info/RECORD
