Metadata-Version: 2.1
Name: newscleaner
Version: 0.2.0
Summary: Package to clean up waste prefix & postfix from articles
Home-page: https://github.com/LakshitaKain/flashnews/tree/dev/cleaner_function
Author: Lakshita Kain
Author-email: lakshita.kain@collegedunia.com
Project-URL: Bug Tracker, https://github.com/LakshitaKain/flashnews/issues
Classifier: Programming Language :: Python :: 3
Classifier: License :: OSI Approved :: MIT License
Classifier: Operating System :: OS Independent
Requires-Python: >=3.8
License-File: LICENCE.txt
